README.rst
setup.py
wishbone_input_disk/__init__.py
wishbone_input_disk/diskin.py
wishbone_input_disk.egg-info/PKG-INFO
wishbone_input_disk.egg-info/SOURCES.txt
wishbone_input_disk.egg-info/dependency_links.txt
wishbone_input_disk.egg-info/entry_points.txt
wishbone_input_disk.egg-info/namespace_packages.txt
wishbone_input_disk.egg-info/not-zip-safe
wishbone_input_disk.egg-info/requires.txt
wishbone_input_disk.egg-info/top_level.txt